bit_vector/__init__.py
bit_vector/bit_vector.py
bit_vector/compatibility.py
bit_vector-0.39a0.dist-info/METADATA
bit_vector-0.39a0.dist-info/RECORD
bit_vector-0.39a0.dist-info/WHEEL
bit_vector-0.39a0.dist-info/top_level.txt
