Metadata-Version: 2.1
Name: bit-vector
Version: 0.39a0
Summary: A BitVector class for Python
Home-page: https://github.com/leonardt/bit_vector
Author: Leonard Truong
Author-email: lenny@cs.stanford.edu
License: UNKNOWN
Platform: UNKNOWN
Requires-Dist: numpy
